LICENSE
MANIFEST.in
README.md
setup.py
jschema2py/__init__.py
jschema2py/cfactory.py
jschema2py/jspymeta.py
jschema2py/property.py
jschema2py/refnavigator.py
jschema2py.egg-info/PKG-INFO
jschema2py.egg-info/SOURCES.txt
jschema2py.egg-info/dependency_links.txt
jschema2py.egg-info/top_level.txt
jschema2py/constraints/__init__.py
jschema2py/constraints/array_constraint.py
jschema2py/constraints/boolean_constraint.py
jschema2py/constraints/constraint.py
jschema2py/constraints/integer_constraint.py
jschema2py/constraints/null_constraint.py
jschema2py/constraints/number_constraint.py
jschema2py/constraints/numeric_constraint.py
jschema2py/constraints/string_constraint.py
jschema2py/constraints/variant_constraint.py