Metadata-Version: 2.1
Name: jschema2py
Version: 0.1.0
Summary: jsonschema to python class converter
Home-page: https://github.com/jacopodl/jschema2py
Author: Jacopo De Luca
Author-email: jacopo.delu@gmail.com
License: MIT
Keywords: jschema2py,json,schema,jsonschema,library,python3
Platform: UNKNOWN
Classifier: Development Status :: 4 - Beta
Classifier: Intended Audience :: Developers
Classifier: License :: OSI Approved :: MIT License
Classifier: Programming Language :: Python :: 3
